LICENSE.txt
README.md
setup.py
epson_escp2/__init__.py
epson_escp2/__main__.py
epson_escp2/__version__.py
epson_escp2/epson_decode.py
epson_escp2/epson_encode.py
epson_escp2/sample.py
epson_escp2/tri_attr.py
epson_escp2.egg-info/PKG-INFO
epson_escp2.egg-info/SOURCES.txt
epson_escp2.egg-info/dependency_links.txt
epson_escp2.egg-info/entry_points.txt
epson_escp2.egg-info/requires.txt
epson_escp2.egg-info/top_level.txt