Metadata-Version: 2.4
Name: epson_escp2
Version: 1.0.2
Summary: A comprehensive module for generating ESC/P2 printer sequences from text or images. Supports markdown-like formatting, tables, and various text styles. It includes a comprehensive ESC/P2 decoder.
Home-page: https://github.com/Ircama/epson_escp2
Author: Ircama
License: EUPL-1.2
Keywords: shell console tkinter
Classifier: Programming Language :: Python :: 3
Classifier: License :: OSI Approved :: European Union Public Licence 1.2 (EUPL 1.2)
Classifier: Topic :: Software Development :: Libraries :: Python Modules
Classifier: Development Status :: 5 - Production/Stable
Classifier: Operating System :: OS Independent
Classifier: Intended Audience :: Developers
Requires-Python: >3.6
License-File: LICENSE.txt
Requires-Dist: pillow
Requires-Dist: hexdump2
Dynamic: author
Dynamic: classifier
Dynamic: description
Dynamic: description-content-type
Dynamic: home-page
Dynamic: keywords
Dynamic: license
Dynamic: license-file
Dynamic: requires-dist
Dynamic: requires-python
Dynamic: summary
